{"cameraMode":{"drawMode":0,"name":"Shaded","section":"Shading Mode"},"sceneLighting":false,"audioPlay":false,"sceneViewState":{"showFog":true,"showMaterialUpdate":false,"showSkybox":false,"showFlares":true,"showImageEffects":true,"showParticleSystems":true},"in2DMode":false,"pivot":{"x":4.999942779541016,"y":0.4999990463256836,"z":10.000337600708008},"rotation":{"x":0.14606378972530366,"y":-0.26935145258903506,"z":0.04136896878480911,"w":0.9510034322738648},"size":46.73527908325195,"orthographic":false}